<?xml version="1.0" encoding="utf-8"?>
<!DOCTYPE hibernate-mapping PUBLIC "-//Hibernate/Hibernate Mapping DTD 3.0//EN"
"http://www.hibernate.org/dtd/hibernate-mapping-3.0.dtd">
<!-- 
    Mapping file autogenerated by MyEclipse Persistence Tools
-->
<hibernate-mapping>
    <class name="com.yunlu.model.DicCrsShieldType" table="y_dic_crs_shield_type" >
        <id name="id" type="integer">
            <column name="id" />
            <generator class="increment" />
        </id>
        <property name="shieldTypeName" type="string">
            <column name="shield_type_name" length="50">
                <comment>课程被屏蔽的类型名称</comment>
            </column>
        </property>
        <property name="sortIndex" type="integer">
            <column name="sort_index">
                <comment>序号</comment>
            </column>
        </property>
        <property name="status" type="integer">
            <column name="status" not-null="true">
                <comment>是否可用（否：0；是：1）</comment>
            </column>
        </property>
    </class>
</hibernate-mapping>
